globus_batch_transfer/__init__.py
globus_batch_transfer/__main__.py
globus_batch_transfer-0.2.0.dist-info/LICENSE
globus_batch_transfer-0.2.0.dist-info/METADATA
globus_batch_transfer-0.2.0.dist-info/WHEEL
globus_batch_transfer-0.2.0.dist-info/RECORD
